latticetools/__init__.py
latticetools/latticetools.py
latticetools/shapes.py
latticetools-0.62.dist-info/LICENSE
latticetools-0.62.dist-info/METADATA
latticetools-0.62.dist-info/WHEEL
latticetools-0.62.dist-info/top_level.txt
latticetools-0.62.dist-info/RECORD
