Metadata-Version: 2.1
Name: latticetools
Version: 0.62
Summary: Makes it easy to manipulate and visualise data on an n-dimensional lattice
Home-page: UNKNOWN
Author: Jack Maxwell
Author-email: latticetools@maxman.cc
License: UNKNOWN
Keywords: lattice grid scientific visualization imaging sampling fourier warp
Platform: UNKNOWN
Classifier: Programming Language :: Python :: 3
Classifier: Operating System :: OS Independent
Classifier: Development Status :: 4 - Beta
Classifier: Intended Audience :: Science/Research
Classifier: License :: OSI Approved :: GNU General Public License v3 or later (GPLv3+)
Classifier: Natural Language :: English
Classifier: Topic :: Scientific/Engineering :: Visualization
Requires-Dist: numpy (>=1.16)
Requires-Dist: matplotlib (>=3)
Requires-Dist: scikit-image (>=0.15)
